anticaptchaofficial/__init__.py
anticaptchaofficial/altchaproxyless.py
anticaptchaofficial/altchaproxyon.py
anticaptchaofficial/amazonproxyless.py
anticaptchaofficial/amazonproxyon.py
anticaptchaofficial/antibotcookietask.py
anticaptchaofficial/antigatetask.py
anticaptchaofficial/antinetworking.py
anticaptchaofficial/friendlycaptchaproxyless.py
anticaptchaofficial/friendlycaptchaproxyon.py
anticaptchaofficial/funcaptchaproxyless.py
anticaptchaofficial/funcaptchaproxyon.py
anticaptchaofficial/geetestproxyless.py
anticaptchaofficial/geetestproxyon.py
anticaptchaofficial/hcaptchaproxyless.py
anticaptchaofficial/hcaptchaproxyon.py
anticaptchaofficial/imagecaptcha.py
anticaptchaofficial/imagecoordinates.py
anticaptchaofficial/imagetocoordinates.py
anticaptchaofficial/prosopoproxyless.py
anticaptchaofficial/prosopoproxyon.py
anticaptchaofficial/recaptchav2enterpriseproxyless.py
anticaptchaofficial/recaptchav2enterpriseproxyon.py
anticaptchaofficial/recaptchav2proxyless.py
anticaptchaofficial/recaptchav2proxyon.py
anticaptchaofficial/recaptchav3enterpriseproxyless.py
anticaptchaofficial/recaptchav3proxyless.py
anticaptchaofficial/turnstileproxyless.py
anticaptchaofficial/turnstileproxyon.py
anticaptchaofficial-1.0.69.dist-info/METADATA
anticaptchaofficial-1.0.69.dist-info/WHEEL
anticaptchaofficial-1.0.69.dist-info/top_level.txt
anticaptchaofficial-1.0.69.dist-info/RECORD
