Metadata-Version: 2.1
Name: anticaptchaofficial
Version: 1.0.69
Summary: Official anti-captcha.com library
Home-page: https://github.com/anti-captcha/anticaptcha-python
Author: Anti Admin
Author-email: admin@anti-captcha.com
License: MIT
Keywords: anticaptcha anti captcha recognition solve bypass recaptcha enterprise funcaptcha arkoselabs geetest hcaptcha antigate turnstile object coordinates prosopo friendly captcha friendlycaptcha amazon waf aws-waf-token
Requires-Dist: py (>=1.4.32)
Requires-Dist: requests (>=2.22.0)
